{"sections":{"rich_text_HVfkCd":{"type":"rich-text","blocks":{"heading_CgK3nG":{"type":"heading","disabled":true,"settings":{"heading":"Try first, pay later😍","heading_size":"h1"}},"text_Vdc8FD":{"type":"text","settings":{"text":"<h2>The <strong>most<\/strong> <strong>convenient <\/strong>way of fashion shopping is here✨<\/h2>"}}},"block_order":["heading_CgK3nG","text_Vdc8FD"],"settings":{"desktop_content_position":"center","content_alignment":"center","color_scheme":"scheme-1","full_width":true,"padding_top":36,"padding_bottom":24}},"rich_text_ARtREF":{"type":"rich-text","blocks":{"heading_4Wf4Ng":{"type":"heading","disabled":true,"settings":{"heading":"Try first, pay later😍","heading_size":"h1"}},"text_mFWTDz":{"type":"text","settings":{"text":"<h3>How Shopin works?<\/h3>"}}},"block_order":["heading_4Wf4Ng","text_mFWTDz"],"settings":{"desktop_content_position":"center","content_alignment":"center","color_scheme":"scheme-1","full_width":true,"padding_top":0,"padding_bottom":0}},"multicolumn_JFppYt":{"type":"multicolumn","blocks":{"column_3G4riX":{"type":"column","settings":{"title":"<strong>🛍️ Create your trial bag<\/strong>","text":"<p>Select upto 10 items that you like & want to try at home.<\/p>","link_label":"","link":""}},"column_ErTJQj":{"type":"column","settings":{"title":"<strong>📦 Schedule delivery<\/strong>","text":"<p>Book a time slot by paying 10% of total bag value. Fully refundable.<\/p>","link_label":"","link":""}},"column_X3tH76":{"type":"column","settings":{"title":"<strong>💃 Try comfortably<\/strong>","text":"<p>We'll bring all your items, and our partner will wait for 30 minutes.<\/p>","link_label":"","link":""}},"column_Qz3nnk":{"type":"column","settings":{"title":"<strong>😍 Keep what you love<\/strong>","text":"<p>Only pay for the items you love! Return what you don't like.<\/p>","link_label":"","link":""}}},"block_order":["column_3G4riX","column_ErTJQj","column_X3tH76","column_Qz3nnk"],"settings":{"title":"","heading_size":"h2","image_width":"full","image_ratio":"adapt","columns_desktop":4,"column_alignment":"left","background_style":"primary","button_label":"","button_link":"","color_scheme":"scheme-1","columns_mobile":"1","swipe_on_mobile":true,"padding_top":12,"padding_bottom":12}},"featured_collection_Vbmffn":{"type":"featured-collection","settings":{"title":"Featured collection","heading_size":"h2","description":"","show_description":false,"description_style":"body","collection":"sale","products_to_show":4,"columns_desktop":4,"full_width":false,"show_view_all":true,"view_all_style":"solid","enable_desktop_slider":false,"color_scheme":"","image_ratio":"adapt","image_shape":"default","show_secondary_image":false,"show_vendor":false,"show_rating":false,"quick_add":"none","columns_mobile":"2","swipe_on_mobile":false,"padding_top":36,"padding_bottom":36}},"collection_list_8npaaX":{"type":"collection-list","blocks":{"featured_collection_Aw9nwp":{"type":"featured_collection","settings":{"collection":"men-under-999-collection"}},"featured_collection_iVmL3e":{"type":"featured_collection","settings":{"collection":"women-under-999-collection"}}},"block_order":["featured_collection_Aw9nwp","featured_collection_iVmL3e"],"settings":{"title":"<strong>H&M under ₹999<\/strong>","heading_size":"h2","image_ratio":"adapt","columns_desktop":2,"color_scheme":"","show_view_all":false,"columns_mobile":"2","swipe_on_mobile":false,"padding_top":12,"padding_bottom":12}},"featured_collection_iT8TAe":{"type":"featured-collection","settings":{"title":"<strong>Explore H&M women<\/strong>","heading_size":"h2","description":"","show_description":false,"description_style":"body","collection":"women-1","products_to_show":4,"columns_desktop":4,"full_width":false,"show_view_all":true,"view_all_style":"solid","enable_desktop_slider":false,"color_scheme":"","image_ratio":"adapt","image_shape":"default","show_secondary_image":true,"show_vendor":false,"show_rating":false,"quick_add":"none","columns_mobile":"2","swipe_on_mobile":false,"padding_top":36,"padding_bottom":12}},"featured_collection_AmiiE4":{"type":"featured-collection","settings":{"title":"<strong>Explore H&M men<\/strong>","heading_size":"h2","description":"","show_description":false,"description_style":"body","collection":"men-1","products_to_show":4,"columns_desktop":4,"full_width":false,"show_view_all":true,"view_all_style":"solid","enable_desktop_slider":false,"color_scheme":"","image_ratio":"adapt","image_shape":"default","show_secondary_image":true,"show_vendor":false,"show_rating":false,"quick_add":"none","columns_mobile":"2","swipe_on_mobile":false,"padding_top":24,"padding_bottom":36}},"collection_list_TUrHPb":{"type":"collection-list","blocks":{"featured_collection_RtJjLj":{"type":"featured_collection","settings":{"collection":"vega-city-collection"}},"featured_collection_wCUUK7":{"type":"featured_collection","settings":{"collection":"1mg-mall-collection"}},"featured_collection_8CNxC3":{"type":"featured_collection","settings":{"collection":"mantri-mall-collection"}},"featured_collection_qJKk4n":{"type":"featured_collection","settings":{"collection":"prestige-falcon-city-collection"}}},"block_order":["featured_collection_RtJjLj","featured_collection_wCUUK7","featured_collection_8CNxC3","featured_collection_qJKk4n"],"disabled":true,"settings":{"title":"H&M stores","heading_size":"h1","image_ratio":"portrait","columns_desktop":4,"color_scheme":"scheme-2","show_view_all":false,"columns_mobile":"2","swipe_on_mobile":false,"padding_top":40,"padding_bottom":12}},"collapsible_content_MtiJTU":{"type":"collapsible-content","blocks":{"collapsible_row_f8aBVq":{"type":"collapsible_row","settings":{"heading":"Are the products 100% authentic?","icon":"none","row_content":"<p>Yes! Shopin sources all items directly from H&M stores. You will also receive a store-generated invoice with every trial order.<\/p>","page":""}},"collapsible_row_AjwYfA":{"type":"collapsible_row","settings":{"heading":"Will I pay the same price as in-store?","icon":"none","row_content":"<p>Absolutely. Our prices are exactly the same as in-store. In fact, you may even receive additional discounts, but we will never charge more than the in-store price.<\/p>","page":""}},"collapsible_row_RfPCYg":{"type":"collapsible_row","settings":{"heading":"Is there a limit on how many items I can add for trial?","icon":"none","row_content":"<p>Currently, you can add between 1 to 10 items per trial. If you need to try more, please reach out to us via email or call.<\/p>","page":""}},"collapsible_row_pb3YYT":{"type":"collapsible_row","settings":{"heading":"What if I need more than 30 minutes to try?","icon":"none","row_content":"<p>Shopin delivery partner will automatically wait an additional 15 minutes. If you need more time, feel free to contact us via email or call.<\/p>","page":""}},"collapsible_row_M8jKCB":{"type":"collapsible_row","settings":{"heading":"If the size doesn’t fit and I like the item, can I exchange?","icon":"none","row_content":"<p>If the size doesn’t fit but you love the item, you can request an exchange:<\/p><p><strong>Same-day exchange:<\/strong> Available within 3 hours if you raise the request before 6:00 PM.<\/p><p><strong>Next-day exchange:<\/strong> Orders placed after 6:00 PM will be exchanged at 11:00 AM the following day.<br\/><br\/><em>Note: Exchange is available only after payment for the item.<\/em><\/p>","page":""}}},"block_order":["collapsible_row_f8aBVq","collapsible_row_AjwYfA","collapsible_row_RfPCYg","collapsible_row_pb3YYT","collapsible_row_M8jKCB"],"settings":{"caption":"","heading":"FAQs","heading_size":"h1","heading_alignment":"center","layout":"none","color_scheme":"scheme-2","container_color_scheme":"","open_first_collapsible_row":false,"image_ratio":"adapt","desktop_layout":"image_second","padding_top":28,"padding_bottom":48}}},"order":["rich_text_HVfkCd","rich_text_ARtREF","multicolumn_JFppYt","featured_collection_Vbmffn","collection_list_8npaaX","featured_collection_iT8TAe","featured_collection_AmiiE4","collection_list_TUrHPb","collapsible_content_MtiJTU"]}